get_cemeb_cal/__init__.py
get_cemeb_cal/__main__.py
get_cemeb_cal-0.1.4.dist-info/COPYING
get_cemeb_cal-0.1.4.dist-info/METADATA
get_cemeb_cal-0.1.4.dist-info/WHEEL
get_cemeb_cal-0.1.4.dist-info/entry_points.txt
get_cemeb_cal-0.1.4.dist-info/top_level.txt
get_cemeb_cal-0.1.4.dist-info/RECORD
