Metadata-Version: 2.1
Name: get_cemeb_cal
Version: 0.1.4
Summary: Get calendar from CeMEB
Author-email: Robert Wolff <mahlzahn@posteo.de>
License: GNU General Public License v3 or later (GPLv3+)
Project-URL: Source, https://codeberg.org/mahlzahn/get_cemeb_cal
Project-URL: Issues, https://codeberg.org/mahlzahn/get_cemeb_cal/issues
Classifier: Development Status :: 4 - Beta
Classifier: Environment :: Console
Classifier: Topic :: Utilities
Classifier: Operating System :: POSIX :: Linux
Classifier: Programming Language :: Python :: 3
Classifier: License :: OSI Approved :: GNU General Public License v3 or later (GPLv3+)
Requires-Python: >=3.8
License-File: COPYING
Requires-Dist: beautifulsoup4
Requires-Dist: icalendar
Requires-Dist: lxml
Requires-Dist: requests
Provides-Extra: full
Requires-Dist: argcomplete ; extra == 'full'
